mcp_science/__init__.py
mcp_science/servers/example-server/.dxtignore
mcp_science/servers/example-server/.python-version
mcp_science/servers/example-server/README.md
mcp_science/servers/example-server/manifest.json
mcp_science/servers/example-server/pyproject.toml
mcp_science/servers/example-server/uv.lock
mcp_science/servers/example-server/src/example_server/__init__.py
mcp_science/servers/example-server/src/example_server/main.py
mcp_science/servers/gpaw-computation/.all-contributorsrc
mcp_science/servers/gpaw-computation/.dxtignore
mcp_science/servers/gpaw-computation/CITATION.cff
mcp_science/servers/gpaw-computation/README.md
mcp_science/servers/gpaw-computation/manifest.json
mcp_science/servers/gpaw-computation/pyproject.toml
mcp_science/servers/gpaw-computation/uv.lock
mcp_science/servers/gpaw-computation/server_package/README.md
mcp_science/servers/gpaw-computation/server_package/pyproject.toml
mcp_science/servers/gpaw-computation/server_package/gpaw_computation_server/__init__.py
mcp_science/servers/gpaw-computation/server_package/gpaw_computation_server/check_calculation_result/__main__.py
mcp_science/servers/gpaw-computation/server_package/gpaw_computation_server/create_calculation_project/__main__.py
mcp_science/servers/gpaw-computation/server_package/gpaw_computation_server/get_project_summary/__main__.py
mcp_science/servers/gpaw-computation/server_package/gpaw_computation_server/gpaw_utils/__init__.py
mcp_science/servers/gpaw-computation/server_package/gpaw_computation_server/gpaw_utils/data_class.py
mcp_science/servers/gpaw-computation/server_package/gpaw_computation_server/gpaw_utils/document.py
mcp_science/servers/gpaw-computation/server_package/gpaw_computation_server/gpaw_utils/lib.py
mcp_science/servers/gpaw-computation/server_package/gpaw_computation_server/gpaw_utils/plot_band_dos_utils.py
mcp_science/servers/gpaw-computation/server_package/gpaw_computation_server/run_calculation/__main__.py
mcp_science-0.1.7.dist-info/METADATA
mcp_science-0.1.7.dist-info/WHEEL
mcp_science-0.1.7.dist-info/entry_points.txt
mcp_science-0.1.7.dist-info/licenses/LICENSE
mcp_science-0.1.7.dist-info/RECORD
