Metadata-Version: 2.4
Name: mcp.science
Version: 0.1.7
Summary: Open Source MCP Servers for Scientific Research
License-File: LICENSE
Requires-Python: >=3.10
Requires-Dist: click>=8.2.1
